dt_extension_migrator/__init__.py
dt_extension_migrator/extension_apps/generic_commands.py
dt_extension_migrator/extension_apps/remote_logs.py
dt_extension_migrator/extension_apps/remote_ntp.py
dt_extension_migrator/extension_apps/remote_unix.py
dt_extension_migrator/logging.py
dt_extension_migrator/main.py
dt_extension_migrator/remote_unix_utils.py
dt_extension_migrator/utility_apps/tags.py
dt_extension_migrator-0.5.7.dist-info/entry_points.txt
dt_extension_migrator-0.5.7.dist-info/METADATA
dt_extension_migrator-0.5.7.dist-info/WHEEL
dt_extension_migrator-0.5.7.dist-info/RECORD
