Metadata-Version: 2.1
Name: dt-extension-migrator
Version: 0.5.7
Summary: 
Author: Your Name
Author-email: you@example.com
Requires-Python: >=3.10,<4.0
Classifier: Programming Language :: Python :: 3
Classifier: Programming Language :: Python :: 3.10
Classifier: Programming Language :: Python :: 3.11
Classifier: Programming Language :: Python :: 3.12
Requires-Dist: dt (>=1.1.66,<2.0.0)
Requires-Dist: pandas (>=2.2.2,<3.0.0)
Requires-Dist: pymmh3 (>=0.0.5,<0.0.6)
Requires-Dist: rich (>=13.7.1,<14.0.0)
Requires-Dist: typer[all] (>=0.12.3,<0.13.0)
Requires-Dist: xlsxwriter (>=3.2.0,<4.0.0)
